__init__.py
agi_node/__init__.py
agi_node/utils.py
agi_node/agi_dispatcher/__init__.py
agi_node/agi_dispatcher/agi_dispatcher.py
agi_node/agi_dispatcher/base_worker.py
agi_node/agi_dispatcher/build.py
agi_node/agi_dispatcher/post_install.py
agi_node/agi_dispatcher/pre_install.py
agi_node/dag_worker/__init__.py
agi_node/dag_worker/dag_worker.py
agi_node/fireducks_worker/__init__.py
agi_node/fireducks_worker/fireducks_worker.py
agi_node/pandas_worker/__init__.py
agi_node/pandas_worker/pandas_worker.py
agi_node/polars_worker/__init__.py
agi_node/polars_worker/polars_worker.py
agi_node-2025.12.19.dist-info/licenses/LICENSE
agi_node-2025.12.19.dist-info/METADATA
agi_node-2025.12.19.dist-info/WHEEL
agi_node-2025.12.19.dist-info/top_level.txt
agi_node-2025.12.19.dist-info/RECORD
