Metadata-Version: 2.4
Name: agi-node
Version: 2025.12.19
Summary: agi-node the local code for AGI framework
Author-email: Jean-Pierre Morard <focus@thalesgroup.com>
Project-URL: Documentation, https://thalesgroup.github.io/agilab
Project-URL: Source, https://github.com/ThalesGroup/agilab/tree/main/src/agilab/core/agi-node
Project-URL: Tracker, https://github.com/ThalesGroup/agilab/issues
Keywords: asyncio,distributed,cluster,dataframe,dataset,agi,datascience
Classifier: Intended Audience :: Developers
Classifier: Development Status :: 3 - Alpha
Classifier: Programming Language :: Python :: 3
Classifier: Programming Language :: Python :: 3.11
Classifier: Programming Language :: Python :: 3.12
Classifier: Programming Language :: Python :: 3.13
Classifier: Operating System :: MacOS
Classifier: Operating System :: Microsoft :: Windows
Classifier: Operating System :: POSIX :: Linux
Requires-Python: >=3.11
License-File: LICENSE
Requires-Dist: scikit-learn
Requires-Dist: parso
Requires-Dist: cython
Requires-Dist: setuptools
Requires-Dist: msgpack
Requires-Dist: numba
Requires-Dist: py7zr
Requires-Dist: python-dotenv
Requires-Dist: tomli
Requires-Dist: dask[distributed]
Requires-Dist: wheel
Requires-Dist: scipy==1.15.2
Requires-Dist: psutil
Requires-Dist: typing-inspection>=0.4.1
Requires-Dist: polars
Requires-Dist: pandas
Requires-Dist: cmake>=3.29
Dynamic: license-file
